transfacpred/blast_binaries/linux/blastp
transfacpred/blast_binaries/mac/blastp
transfacpred/blast_binaries/windows/blastp.exe
transfacpred/blast_binaries/windows/nghttp2.dll
transfacpred/python_scripts/__init__.py
transfacpred/python_scripts/transfacpred.py
transfacpred-1.1.1.dist-info/LICENSE.txt
transfacpred-1.1.1.dist-info/METADATA
transfacpred-1.1.1.dist-info/WHEEL
transfacpred-1.1.1.dist-info/entry_points.txt
transfacpred-1.1.1.dist-info/top_level.txt
transfacpred-1.1.1.dist-info/RECORD
