Metadata-Version: 2.1
Name: transfacpred
Version: 1.1.1
Summary: A method to predict the transcription factors using protein sequences.
Home-page: https://github.com/raghavagps/transfacpred
Requires-Python: >=3.6
License-File: LICENSE.txt
Requires-Dist: numpy
Requires-Dist: pandas
Requires-Dist: scikit-learn
